[{"title":"byparker.com","endpoint":"https://byparker.com","timestamp":1510257601822445735,"times":[{"rtt":75814918},{"rtt":30700516},{"rtt":44112085},{"rtt":33629492},{"rtt":36125897}],"healthy":true},{"title":"parkermoo.re","endpoint":"https://parkermoo.re","timestamp":1510257601822533649,"times":[{"rtt":173818943},{"rtt":47656158},{"rtt":38159295},{"rtt":28706819},{"rtt":24314306}],"healthy":true},{"title":"gossip.parkermoo.re","endpoint":"https://gossip.parkermoo.re","timestamp":1510257601824024825,"times":[{"rtt":161511081},{"rtt":44712207},{"rtt":34735073},{"rtt":32978380},{"rtt":31305690}],"healthy":true},{"title":"irc.parkermoo.re","endpoint":"https://irc.parkermoo.re","timestamp":1510257601822975632,"times":[{"rtt":84757597},{"rtt":35320933},{"rtt":55019798},{"rtt":43707090},{"rtt":38186133}],"healthy":true},{"title":"ping.parkermoo.re","endpoint":"https://ping.parkermoo.re/_health","timestamp":1510257601822435160,"times":[{"rtt":111943415},{"rtt":38736805},{"rtt":46266884},{"rtt":36772721},{"rtt":28492278}],"healthy":true},{"title":"stuff.parkermoore.de","endpoint":"https://stuff.parkermoore.de","timestamp":1510257602042965407,"times":[{"rtt":58640098},{"rtt":31590519},{"rtt":49397364},{"rtt":34824337},{"rtt":37589209}],"healthy":true},{"title":"stash.byparker.com","endpoint":"https://stash.byparker.com","timestamp":1510257602080304125,"times":[{"rtt":47865949},{"rtt":41435538},{"rtt":31774497},{"rtt":34851888},{"rtt":33353862}],"healthy":true},{"title":"pages.byparker.com","endpoint":"https://pages.byparker.com","timestamp":1510257602084726914,"times":[{"rtt":129588619},{"rtt":38008179},{"rtt":36752208},{"rtt":42045586},{"rtt":32277068}],"healthy":true},{"title":"plex server","endpoint":"http://127.0.0.1:32400","timestamp":1510257602129383208,"times":[{"rtt":2399029}],"healthy":true},{"title":"github.com/parkr","endpoint":"https://github.com/parkr","timestamp":1510257602131840375,"times":[{"rtt":515475225}],"healthy":true}]