[{"title":"byparker.com","endpoint":"https://byparker.com","timestamp":1558143002659390494,"times":[{"rtt":210331510},{"rtt":116404459},{"rtt":86565917},{"rtt":85595035},{"rtt":90692562}],"threshold":400000000,"healthy":true},{"title":"parkermoo.re","endpoint":"https://parkermoo.re","timestamp":1558143002659060375,"times":[{"rtt":226634633},{"rtt":137232235},{"rtt":126013538},{"rtt":116113616},{"rtt":132602406}],"threshold":400000000,"healthy":true},{"title":"gossip.parkermoo.re","endpoint":"https://gossip.parkermoo.re","timestamp":1558143002659869053,"times":[{"rtt":243642296},{"rtt":139872687},{"rtt":114601936},{"rtt":101819257},{"rtt":131401269}],"threshold":400000000,"healthy":true},{"title":"irc.parkermoo.re","endpoint":"https://irc.parkermoo.re","timestamp":1558143002659569247,"times":[{"rtt":224516103},{"rtt":137542053},{"rtt":109157628},{"rtt":147245959},{"rtt":119497596}],"threshold":400000000,"healthy":true},{"title":"ping.parkermoo.re","endpoint":"https://ping.parkermoo.re/_health","timestamp":1558143002659005036,"times":[{"rtt":222391737},{"rtt":133923807},{"rtt":124546159},{"rtt":106772181},{"rtt":108138332}],"threshold":400000000,"healthy":true},{"title":"stuff.parkermoore.de","endpoint":"https://stuff.parkermoore.de","timestamp":1558143003250078011,"times":[{"rtt":537508913},{"rtt":84345910},{"rtt":98219773},{"rtt":73909841},{"rtt":91510916}],"threshold":400000000,"healthy":true},{"title":"stash.byparker.com","endpoint":"https://stash.byparker.com","timestamp":1558143003355548904,"times":[{"rtt":434002772},{"rtt":80490159},{"rtt":77229907},{"rtt":90276541},{"rtt":85199415}],"threshold":400000000,"healthy":true},{"title":"keltermoore.com","endpoint":"https://www.keltermoore.com","timestamp":1558143003392781668,"times":[{"rtt":394391473},{"rtt":83069097},{"rtt":78651460},{"rtt":88588194},{"rtt":85092675}],"threshold":400000000,"healthy":true},{"title":"plex server","endpoint":"http://127.0.0.1:32400","timestamp":1558143003398288689,"times":[{"rtt":3341928}],"threshold":200000000,"healthy":true},{"title":"plants","endpoint":"https://plants.keltermoore.com","timestamp":1558143003398608921,"times":[{"rtt":145062640}],"threshold":400000000,"healthy":true},{"title":"github.com/parkr","endpoint":"https://github.com/parkr","timestamp":1558143003402040176,"times":[{"rtt":701596830}],"threshold":4000000000,"healthy":true}]