[{"title":"byparker.com","endpoint":"https://byparker.com","timestamp":1558614602565696315,"times":[{"rtt":222305503},{"rtt":75202326},{"rtt":90834992},{"rtt":76865607},{"rtt":79195237}],"threshold":400000000,"healthy":true},{"title":"parkermoo.re","endpoint":"https://parkermoo.re","timestamp":1558614602564920063,"times":[{"rtt":214544308},{"rtt":130086073},{"rtt":117982397},{"rtt":105715594},{"rtt":106758226}],"threshold":400000000,"healthy":true},{"title":"gossip.parkermoo.re","endpoint":"https://gossip.parkermoo.re","timestamp":1558614602564973077,"times":[{"rtt":227074954},{"rtt":104771514},{"rtt":117090344},{"rtt":124168887},{"rtt":114491557}],"threshold":400000000,"healthy":true},{"title":"irc.parkermoo.re","endpoint":"https://irc.parkermoo.re","timestamp":1558614602564981514,"times":[{"rtt":495927036},{"rtt":119373886},{"rtt":106723763},{"rtt":120072536},{"rtt":129362622}],"threshold":400000000,"healthy":true},{"title":"ping.parkermoo.re","endpoint":"https://ping.parkermoo.re/_health","timestamp":1558614602564876575,"times":[{"rtt":223767942},{"rtt":113430250},{"rtt":112179727},{"rtt":119667642},{"rtt":98789565}],"threshold":400000000,"healthy":true},{"title":"stuff.parkermoore.de","endpoint":"https://stuff.parkermoore.de","timestamp":1558614603111013759,"times":[{"rtt":238832999},{"rtt":87159261},{"rtt":79403267},{"rtt":97698532},{"rtt":84154842}],"threshold":400000000,"healthy":true},{"title":"stash.byparker.com","endpoint":"https://stash.byparker.com","timestamp":1558614603234594986,"times":[{"rtt":125193231},{"rtt":86105154},{"rtt":81114386},{"rtt":89481841},{"rtt":86097879}],"threshold":400000000,"healthy":true},{"title":"keltermoore.com","endpoint":"https://www.keltermoore.com","timestamp":1558614603242108201,"times":[{"rtt":111120645},{"rtt":81726784},{"rtt":78400672},{"rtt":83552606},{"rtt":84855318}],"threshold":400000000,"healthy":true},{"title":"plex server","endpoint":"http://127.0.0.1:32400","timestamp":1558614603253675166,"times":[{"rtt":1402789}],"threshold":200000000,"healthy":true},{"title":"plants","endpoint":"https://plants.keltermoore.com","timestamp":1558614603255260471,"times":[{"rtt":131601389}],"threshold":400000000,"healthy":true},{"title":"github.com/parkr","endpoint":"https://github.com/parkr","timestamp":1558614603387047075,"times":[{"rtt":1398815830}],"threshold":4000000000,"healthy":true}]