[{"title":"byparker.com","endpoint":"https://byparker.com","timestamp":1580779802524645291,"times":[{"rtt":144320570},{"rtt":53348136},{"rtt":68167534},{"rtt":58544940},{"rtt":45794753}],"threshold":400000000,"healthy":true},{"title":"parkermoo.re","endpoint":"https://parkermoo.re","timestamp":1580779802523417382,"times":[{"rtt":160464440},{"rtt":95591589},{"rtt":77553610},{"rtt":80794392},{"rtt":96494044}],"threshold":400000000,"healthy":true},{"title":"gossip.parkermoo.re","endpoint":"https://gossip.parkermoo.re","timestamp":1580779802525397579,"times":[{"rtt":194750717},{"rtt":102156667},{"rtt":100917233},{"rtt":92793891},{"rtt":88575466}],"threshold":400000000,"healthy":true},{"title":"irc.parkermoo.re","endpoint":"https://irc.parkermoo.re","timestamp":1580779802527603893,"times":[{"rtt":178895939},{"rtt":104046313},{"rtt":103169747},{"rtt":101468368},{"rtt":103354963}],"threshold":400000000,"healthy":true},{"title":"ping.parkermoo.re","endpoint":"https://ping.parkermoo.re/_health","timestamp":1580779802526178943,"times":[{"rtt":157331048},{"rtt":96949914},{"rtt":85534501},{"rtt":82703551},{"rtt":94343930}],"threshold":400000000,"healthy":true},{"title":"stuff.parkermoore.de","endpoint":"https://stuff.parkermoore.de","timestamp":1580779802895511472,"times":[{"rtt":143716721},{"rtt":60552062},{"rtt":56889423},{"rtt":57095439},{"rtt":57707462}],"threshold":400000000,"healthy":true},{"title":"stash.byparker.com","endpoint":"https://stash.byparker.com","timestamp":1580779803035275237,"times":[{"rtt":89790012},{"rtt":60988995},{"rtt":55855417},{"rtt":60259233},{"rtt":58188897}],"threshold":400000000,"healthy":true},{"title":"keltermoore.com","endpoint":"https://www.keltermoore.com","timestamp":1580779803043644959,"times":[{"rtt":69753411},{"rtt":51932787},{"rtt":57478071},{"rtt":56897274},{"rtt":52007613}],"threshold":400000000,"healthy":true},{"title":"plex server","endpoint":"http://127.0.0.1:32400","timestamp":1580779803105481056,"times":[{"rtt":1791106}],"threshold":200000000,"healthy":true},{"title":"plants","endpoint":"https://plants.keltermoore.com/ping","timestamp":1580779803107504742,"times":[{"rtt":110676517},{"rtt":93472328},{"rtt":110911058},{"rtt":102390071},{"rtt":95846107}],"threshold":400000000,"healthy":true}]