[{"title":"byparker.com","endpoint":"https://byparker.com","timestamp":1581755402450088291,"times":[{"rtt":183619092},{"rtt":74570953},{"rtt":58422544},{"rtt":60298280},{"rtt":59156271}],"threshold":400000000,"healthy":true},{"title":"parkermoo.re","endpoint":"https://parkermoo.re","timestamp":1581755402450591025,"times":[{"rtt":207360197},{"rtt":108048919},{"rtt":88198752},{"rtt":110120959},{"rtt":84840563}],"threshold":400000000,"healthy":true},{"title":"gossip.parkermoo.re","endpoint":"https://gossip.parkermoo.re","timestamp":1581755402450954545,"times":[{"rtt":240261390},{"rtt":101390093},{"rtt":86256689},{"rtt":112056747},{"rtt":94223117}],"threshold":400000000,"healthy":true},{"title":"irc.parkermoo.re","endpoint":"https://irc.parkermoo.re","timestamp":1581755402451175862,"times":[{"rtt":241087093},{"rtt":95646945},{"rtt":108206585},{"rtt":102468913},{"rtt":107973030}],"threshold":400000000,"healthy":true},{"title":"ping.parkermoo.re","endpoint":"https://ping.parkermoo.re/_health","timestamp":1581755402449230712,"times":[{"rtt":211599878},{"rtt":109273944},{"rtt":84132462},{"rtt":87086668},{"rtt":89981198}],"threshold":400000000,"healthy":true},{"title":"stuff.parkermoore.de","endpoint":"https://stuff.parkermoore.de","timestamp":1581755402887019448,"times":[{"rtt":113541725},{"rtt":191015809},{"rtt":57470038},{"rtt":49538436},{"rtt":61034057}],"threshold":400000000,"healthy":true},{"title":"stash.byparker.com","endpoint":"https://stash.byparker.com","timestamp":1581755403031956237,"times":[{"rtt":105576835},{"rtt":75605023},{"rtt":69049835},{"rtt":95332989},{"rtt":60807427}],"threshold":400000000,"healthy":true},{"title":"keltermoore.com","endpoint":"https://www.keltermoore.com","timestamp":1581755403050100622,"times":[{"rtt":58491408},{"rtt":61093307},{"rtt":47022639},{"rtt":40896159},{"rtt":52460630}],"threshold":400000000,"healthy":true},{"title":"plex server","endpoint":"http://127.0.0.1:32400","timestamp":1581755403085793581,"times":[{"rtt":2303619}],"threshold":200000000,"healthy":true},{"title":"plants","endpoint":"https://plants.keltermoore.com/ping","timestamp":1581755403088337817,"times":[{"rtt":138268236},{"rtt":169374519},{"rtt":1688337278},{"rtt":111466247},{"rtt":86690223}],"threshold":400000000,"healthy":true}]