[{"title":"byparker.com","endpoint":"https://byparker.com","timestamp":1587695402630600693,"times":[{"rtt":213208364},{"rtt":146485220},{"rtt":118171790},{"rtt":213546689},{"rtt":84521819}],"threshold":400000000,"healthy":true},{"title":"parkermoo.re","endpoint":"https://parkermoo.re","timestamp":1587695402630206915,"times":[{"rtt":222068450},{"rtt":161740216},{"rtt":116078142},{"rtt":192960900},{"rtt":101975730}],"threshold":400000000,"healthy":true},{"title":"gossip.parkermoo.re","endpoint":"https://gossip.parkermoo.re","timestamp":1587695402630755575,"times":[{"rtt":230718277},{"rtt":206125074},{"rtt":188501681},{"rtt":147737895},{"rtt":142282811}],"threshold":400000000,"healthy":true},{"title":"irc.parkermoo.re","endpoint":"https://irc.parkermoo.re","timestamp":1587695402630981097,"times":[{"rtt":233307033},{"rtt":199039961},{"rtt":179686809},{"rtt":151039842},{"rtt":107783042}],"threshold":400000000,"healthy":true},{"title":"ping.parkermoo.re","endpoint":"https://ping.parkermoo.re/_health","timestamp":1587695402630088710,"times":[{"rtt":207308448},{"rtt":177453532},{"rtt":114142051},{"rtt":127913212},{"rtt":119492894}],"threshold":400000000,"healthy":true},{"title":"stuff.parkermoore.de","endpoint":"https://stuff.parkermoore.de","timestamp":1587695403377513218,"times":[{"rtt":241342684},{"rtt":125125311},{"rtt":93292801},{"rtt":98344782},{"rtt":73306000}],"threshold":400000000,"healthy":true},{"title":"stash.byparker.com","endpoint":"https://stash.byparker.com","timestamp":1587695403407381047,"times":[{"rtt":302271967},{"rtt":82693345},{"rtt":98666882},{"rtt":68259519},{"rtt":65079977}],"threshold":400000000,"healthy":true},{"title":"keltermoore.com","endpoint":"https://www.keltermoore.com","timestamp":1587695403426005869,"times":[{"rtt":194413797},{"rtt":120203561},{"rtt":87730825},{"rtt":94506814},{"rtt":80486166}],"threshold":400000000,"healthy":true},{"title":"plex server","endpoint":"http://127.0.0.1:32400","timestamp":1587695403503044046,"times":[{"rtt":1645254}],"threshold":10000000,"healthy":true},{"title":"plants","endpoint":"https://plants.keltermoore.com/ping","timestamp":1587695403504846782,"times":[{"rtt":85989816},{"rtt":132417171},{"rtt":107377538},{"rtt":104308362},{"rtt":96844283}],"threshold":400000000,"healthy":true},{"title":"parker.codes","endpoint":"https://parker.codes/","timestamp":1587695403546693762,"times":[{"rtt":126614635}],"threshold":400000000,"healthy":true}]