[{"title":"byparker.com","endpoint":"https://byparker.com","timestamp":1592820002256064331,"times":[{"rtt":357137643},{"rtt":56108457},{"rtt":46865962},{"rtt":37671981},{"rtt":31625999}],"threshold":400000000,"healthy":true},{"title":"parkermoo.re","endpoint":"https://parkermoo.re","timestamp":1592820002255758550,"times":[{"rtt":352546128},{"rtt":78562537},{"rtt":72987152},{"rtt":62096788},{"rtt":59658227}],"threshold":400000000,"healthy":true},{"title":"gossip.parkermoo.re","endpoint":"https://gossip.parkermoo.re","timestamp":1592820002255822776,"times":[{"rtt":372924492},{"rtt":74635360},{"rtt":88196302},{"rtt":76807164},{"rtt":71950420}],"threshold":400000000,"healthy":true},{"title":"irc.parkermoo.re","endpoint":"https://irc.parkermoo.re","timestamp":1592820002256208546,"times":[{"rtt":373597143},{"rtt":110212386},{"rtt":92468736},{"rtt":64356094},{"rtt":85202143}],"threshold":400000000,"healthy":true},{"title":"ping.parkermoo.re","endpoint":"https://ping.parkermoo.re/_health","timestamp":1592820002255696049,"times":[{"rtt":367945870},{"rtt":110669433},{"rtt":89777270},{"rtt":58146647},{"rtt":62490157}],"threshold":400000000,"healthy":true},{"title":"stuff.parkermoore.de","endpoint":"https://stuff.parkermoore.de","timestamp":1592820002786268751,"times":[{"rtt":316189461},{"rtt":41527907},{"rtt":63897123},{"rtt":42787231},{"rtt":41874776}],"threshold":400000000,"healthy":true},{"title":"stash.byparker.com","endpoint":"https://stash.byparker.com","timestamp":1592820002882402184,"times":[{"rtt":89727207},{"rtt":51210935},{"rtt":125874770},{"rtt":65731734},{"rtt":57036150}],"threshold":400000000,"healthy":true},{"title":"keltermoore.com","endpoint":"https://www.keltermoore.com","timestamp":1592820002945304112,"times":[{"rtt":202599546},{"rtt":62396444},{"rtt":55993954},{"rtt":36419506},{"rtt":39706058}],"threshold":400000000,"healthy":true},{"title":"plex server","endpoint":"http://127.0.0.1:32400","timestamp":1592820002946063890,"times":[{"rtt":1901638}],"threshold":10000000,"healthy":true},{"title":"plants","endpoint":"https://plants.keltermoore.com/ping","timestamp":1592820002948176069,"times":[{"rtt":214310914},{"rtt":60766086},{"rtt":73965633},{"rtt":69249653},{"rtt":80809307}],"threshold":400000000,"healthy":true},{"title":"parker.codes","endpoint":"https://parker.codes/","timestamp":1592820002983174959,"times":[{"rtt":182252519}],"threshold":400000000,"healthy":true}]