[{"title":"byparker.com","endpoint":"https://byparker.com","timestamp":1598558402134522745,"times":[{"rtt":341495097},{"rtt":63600803},{"rtt":41213408},{"rtt":47318192},{"rtt":46214020}],"threshold":400000000,"healthy":true},{"title":"parkermoo.re","endpoint":"https://parkermoo.re","timestamp":1598558402134044198,"times":[{"rtt":338224394},{"rtt":70017906},{"rtt":64250516},{"rtt":62976828},{"rtt":63180670}],"threshold":400000000,"healthy":true},{"title":"gossip.parkermoo.re","endpoint":"https://gossip.parkermoo.re","timestamp":1598558402134599147,"times":[{"rtt":349851962},{"rtt":76939207},{"rtt":57521044},{"rtt":69921680},{"rtt":57761899}],"threshold":400000000,"healthy":true},{"title":"irc.parkermoo.re","endpoint":"https://irc.parkermoo.re","timestamp":1598558402135326924,"times":[{"rtt":340545102},{"rtt":85727144},{"rtt":74588222},{"rtt":93914657},{"rtt":84852726}],"threshold":400000000,"healthy":true},{"title":"ping.parkermoo.re","endpoint":"https://ping.parkermoo.re/_health","timestamp":1598558402134015698,"times":[{"rtt":346916916},{"rtt":80656893},{"rtt":73862733},{"rtt":88515024},{"rtt":57015284}],"threshold":400000000,"healthy":true},{"title":"stuff.parkermoore.de","endpoint":"https://stuff.parkermoore.de","timestamp":1598558402674859236,"times":[{"rtt":225721117},{"rtt":59768302},{"rtt":56810993},{"rtt":53846121},{"rtt":45348753}],"threshold":400000000,"healthy":true},{"title":"stash.byparker.com","endpoint":"https://stash.byparker.com","timestamp":1598558402733541054,"times":[{"rtt":138134286},{"rtt":57056036},{"rtt":60299875},{"rtt":58695306},{"rtt":53050380}],"threshold":400000000,"healthy":true},{"title":"keltermoore.com","endpoint":"https://www.keltermoore.com","timestamp":1598558402747246664,"times":[{"rtt":169718216},{"rtt":68362798},{"rtt":46828557},{"rtt":42385231},{"rtt":55786097}],"threshold":400000000,"healthy":true},{"title":"plex server","endpoint":"http://127.0.0.1:32400","timestamp":1598558402781602873,"times":[{"rtt":2023427}],"threshold":10000000,"healthy":true},{"title":"plants","endpoint":"https://plants.keltermoore.com/ping","timestamp":1598558402783760666,"times":[{"rtt":221220977},{"rtt":68713855},{"rtt":72857712},{"rtt":61569925},{"rtt":78473099}],"threshold":400000000,"healthy":true},{"title":"parker.codes","endpoint":"https://parker.codes/","timestamp":1598558402816046171,"times":[{"rtt":169316520}],"threshold":400000000,"healthy":true}]