[{"title":"byparker.com","endpoint":"https://byparker.com","timestamp":1625644801940355812,"times":[{"rtt":2244547493},{"rtt":57481698},{"rtt":71363907},{"rtt":66925445},{"rtt":51982391}],"threshold":400000000,"healthy":true},{"title":"parkermoo.re","endpoint":"https://parkermoo.re","timestamp":1625644801940266310,"times":[{"rtt":2253211912},{"rtt":68786369},{"rtt":59868582},{"rtt":66124054},{"rtt":65976227}],"threshold":400000000,"healthy":true},{"title":"gossip.parkermoo.re","endpoint":"https://gossip.parkermoo.re","timestamp":1625644801940355812,"times":[{"rtt":2258908385},{"rtt":88824748},{"rtt":72381576},{"rtt":75970634},{"rtt":71541623}],"threshold":400000000,"healthy":true},{"title":"irc.parkermoo.re","endpoint":"https://irc.parkermoo.re","timestamp":1625644801940396325,"times":[{"rtt":2259031600},{"rtt":93033506},{"rtt":78767839},{"rtt":72136622},{"rtt":62731938}],"threshold":400000000,"healthy":true},{"title":"ping.parkermoo.re","endpoint":"https://ping.parkermoo.re/_health","timestamp":1625644801940250060,"times":[{"rtt":2259586224},{"rtt":92983017},{"rtt":78494271},{"rtt":65379840},{"rtt":60853302}],"threshold":400000000,"healthy":true},{"title":"stuff.parkermoore.de","endpoint":"https://stuff.parkermoore.de","timestamp":1625644804433411209,"times":[{"rtt":147595508},{"rtt":60988154},{"rtt":40007769},{"rtt":45480563},{"rtt":39471096}],"threshold":400000000,"healthy":true},{"title":"stash.byparker.com","endpoint":"https://stash.byparker.com","timestamp":1625644804455077420,"times":[{"rtt":5085994620},{"rtt":47087858},{"rtt":67769662},{"rtt":45744581},{"rtt":45035118}],"threshold":400000000,"healthy":true},{"title":"keltermoore.com","endpoint":"https://www.keltermoore.com","timestamp":1625644804498692485,"times":[{"rtt":75153144},{"rtt":36789857},{"rtt":46525472},{"rtt":30763201},{"rtt":43791118}],"threshold":400000000,"healthy":true},{"title":"plex server","endpoint":"http://127.0.0.1:32400","timestamp":1625644804507109937,"times":[{"rtt":2184092}],"threshold":10000000,"healthy":true},{"title":"plants","endpoint":"https://plants.keltermoore.com/ping","timestamp":1625644804509627774,"times":[{"rtt":75611478},{"rtt":72649982},{"rtt":74452079},{"rtt":81148748},{"rtt":74503444}],"threshold":400000000,"healthy":true},{"title":"parker.codes","endpoint":"https://parker.codes/","timestamp":1625644804509728275,"times":[{"rtt":62519347}],"threshold":400000000,"healthy":true}]