[{"title":"byparker.com","endpoint":"https://byparker.com","timestamp":1649401201962879736,"times":[{"rtt":2305940170},{"rtt":56576771},{"rtt":34703435},{"rtt":54464605},{"rtt":33986671}],"threshold":400000000,"healthy":true},{"title":"parkermoo.re","endpoint":"https://parkermoo.re","timestamp":1649401201963260494,"times":[{"rtt":2330894391},{"rtt":249078700},{"rtt":251828829},{"rtt":247333117},{"rtt":303575880}],"threshold":400000000,"healthy":true},{"title":"gossip.parkermoo.re","endpoint":"https://gossip.parkermoo.re","timestamp":1649401201963162567,"times":[{"rtt":2309490076},{"rtt":254189312},{"rtt":241136496},{"rtt":238642598},{"rtt":246037353}],"threshold":400000000,"healthy":true},{"title":"irc.parkermoo.re","endpoint":"https://irc.parkermoo.re","timestamp":1649401201963484010,"times":[{"rtt":2317425304},{"rtt":248143432},{"rtt":247392255},{"rtt":247409855},{"rtt":252994976}],"threshold":400000000,"healthy":true},{"title":"ping.parkermoo.re","endpoint":"https://ping.parkermoo.re/_health","timestamp":1649401201962883161,"times":[{"rtt":2318487801},{"rtt":249915879},{"rtt":256369191},{"rtt":242637401},{"rtt":245784699}],"threshold":400000000,"healthy":true},{"title":"stuff.parkermoore.de","endpoint":"https://stuff.parkermoore.de","timestamp":1649401204449290015,"times":[{"rtt":143454979},{"rtt":53392759},{"rtt":76562621},{"rtt":36215652},{"rtt":49516409}],"threshold":400000000,"healthy":true},{"title":"stash.byparker.com","endpoint":"https://stash.byparker.com","timestamp":1649401204809213562,"times":[{"rtt":166383585},{"rtt":35644503},{"rtt":43165274},{"rtt":59782070},{"rtt":50115483}],"threshold":400000000,"healthy":true},{"title":"keltermoore.com","endpoint":"https://www.keltermoore.com","timestamp":1649401205165020905,"times":[{"rtt":158222715},{"rtt":50789484},{"rtt":51657501},{"rtt":50346888},{"rtt":59904810}],"threshold":400000000,"healthy":true},{"title":"plex server","endpoint":"http://127.0.0.1:32400","timestamp":1649401205253501369,"times":[{"rtt":5372205}],"threshold":10000000,"healthy":true},{"title":"plants","endpoint":"https://plants.keltermoore.com/ping","timestamp":1649401205259296056,"times":[{"rtt":251166753},{"rtt":257207620},{"rtt":249477821},{"rtt":253888932},{"rtt":243352314}],"threshold":400000000,"healthy":true},{"title":"parker.codes","endpoint":"https://parker.codes/","timestamp":1649401205277500546,"times":[{"rtt":238219727}],"threshold":400000000,"healthy":true}]