[{"title":"byparker.com","endpoint":"https://byparker.com","timestamp":1656748802785843913,"times":[{"rtt":2426264242},{"rtt":37227772},{"rtt":69745616},{"rtt":42433299},{"rtt":64233884}],"threshold":400000000,"healthy":true},{"title":"parkermoo.re","endpoint":"https://parkermoo.re","timestamp":1656748802785707722,"times":[{"rtt":2463028605},{"rtt":235373694},{"rtt":247616730},{"rtt":239685640},{"rtt":240635458}],"threshold":400000000,"healthy":true},{"title":"gossip.parkermoo.re","endpoint":"https://gossip.parkermoo.re","timestamp":1656748802785704472,"times":[{"rtt":2499561638},{"rtt":238982363},{"rtt":249683971},{"rtt":241474486},{"rtt":243417712}],"threshold":400000000,"healthy":true},{"title":"irc.parkermoo.re","endpoint":"https://irc.parkermoo.re","timestamp":1656748802786128281,"times":[{"rtt":2480225901,"error":"response status 302 Moved Temporarily"},{"rtt":239961545,"error":"response status 302 Moved Temporarily"},{"rtt":249717109,"error":"response status 302 Moved Temporarily"},{"rtt":239135866,"error":"response status 302 Moved Temporarily"},{"rtt":235974868,"error":"response status 302 Moved Temporarily"}],"threshold":400000000,"down":true},{"title":"ping.parkermoo.re","endpoint":"https://ping.parkermoo.re/_health","timestamp":1656748802788829620,"times":[{"rtt":2469495655},{"rtt":239817680},{"rtt":238916812},{"rtt":244344242},{"rtt":240485192}],"threshold":400000000,"healthy":true},{"title":"stuff.parkermoore.de","endpoint":"https://stuff.parkermoore.de","timestamp":1656748805426529215,"times":[{"rtt":144590356},{"rtt":46514078},{"rtt":56203554},{"rtt":44443750},{"rtt":40376284}],"threshold":400000000,"healthy":true},{"title":"stash.byparker.com","endpoint":"https://stash.byparker.com","timestamp":1656748805759640143,"times":[{"rtt":138023466},{"rtt":47412007},{"rtt":67439521},{"rtt":37665318},{"rtt":54965404}],"threshold":400000000,"healthy":true},{"title":"keltermoore.com","endpoint":"https://www.keltermoore.com","timestamp":1656748806105889626,"times":[{"rtt":138201307},{"rtt":37160984},{"rtt":50257638},{"rtt":42550738},{"rtt":46542916}],"threshold":400000000,"healthy":true},{"title":"plex server","endpoint":"http://127.0.0.1:32400","timestamp":1656748806213146545,"times":[{"rtt":2063277}],"threshold":10000000,"healthy":true},{"title":"plants","endpoint":"https://plants.keltermoore.com/ping","timestamp":1656748806215347838,"times":[{"rtt":249737422},{"rtt":247845035},{"rtt":252336136},{"rtt":257336069},{"rtt":251270415}],"threshold":400000000,"healthy":true},{"title":"parker.codes","endpoint":"https://parker.codes/","timestamp":1656748806222512814,"times":[{"rtt":246914567}],"threshold":400000000,"healthy":true}]