[{"title":"byparker.com","endpoint":"https://byparker.com","timestamp":1657927802337618065,"times":[{"rtt":2287640908},{"rtt":51894358},{"rtt":39787761},{"rtt":50336703},{"rtt":43653898}],"threshold":400000000,"healthy":true},{"title":"parkermoo.re","endpoint":"https://parkermoo.re","timestamp":1657927802337380923,"times":[{"rtt":2328972411},{"rtt":252768637},{"rtt":254591848},{"rtt":228156196},{"rtt":248656132}],"threshold":400000000,"healthy":true},{"title":"gossip.parkermoo.re","endpoint":"https://gossip.parkermoo.re","timestamp":1657927802337954147,"times":[{"rtt":2328456101},{"rtt":236425119},{"rtt":255825485},{"rtt":238464134},{"rtt":238204579}],"threshold":400000000,"healthy":true},{"title":"irc.parkermoo.re","endpoint":"https://irc.parkermoo.re","timestamp":1657927802337606840,"times":[{"rtt":2339202673,"error":"response status 302 Moved Temporarily"},{"rtt":250789774,"error":"response status 302 Moved Temporarily"},{"rtt":266152972,"error":"response status 302 Moved Temporarily"},{"rtt":238755290,"error":"response status 302 Moved Temporarily"},{"rtt":235065581,"error":"response status 302 Moved Temporarily"}],"threshold":400000000,"down":true},{"title":"ping.parkermoo.re","endpoint":"https://ping.parkermoo.re/_health","timestamp":1657927802337367673,"times":[{"rtt":2330462816},{"rtt":241412892},{"rtt":233686717},{"rtt":243411656},{"rtt":257224774}],"threshold":400000000,"healthy":true},{"title":"stuff.parkermoore.de","endpoint":"https://stuff.parkermoore.de","timestamp":1657927804811643996,"times":[{"rtt":141825769},{"rtt":39047871},{"rtt":54162065},{"rtt":103482336},{"rtt":37892599}],"threshold":400000000,"healthy":true},{"title":"stash.byparker.com","endpoint":"https://stash.byparker.com","timestamp":1657927805188819089,"times":[{"rtt":150095079},{"rtt":47888430},{"rtt":44953024},{"rtt":52832514},{"rtt":105038567}],"threshold":400000000,"healthy":true},{"title":"keltermoore.com","endpoint":"https://www.keltermoore.com","timestamp":1657927805590426881,"times":[{"rtt":234287777},{"rtt":46680782},{"rtt":40899732},{"rtt":50614671},{"rtt":46455052}],"threshold":400000000,"healthy":true},{"title":"plex server","endpoint":"http://127.0.0.1:32400","timestamp":1657927805636088443,"times":[{"rtt":3374628}],"threshold":10000000,"healthy":true},{"title":"plants","endpoint":"https://plants.keltermoore.com/ping","timestamp":1657927805639691513,"times":[{"rtt":286034497},{"rtt":245011325},{"rtt":248439228},{"rtt":246952100},{"rtt":247979069}],"threshold":400000000,"healthy":true},{"title":"parker.codes","endpoint":"https://parker.codes/","timestamp":1657927805645141556,"times":[{"rtt":244967323}],"threshold":400000000,"healthy":true}]