[{"title":"byparker.com","endpoint":"https://byparker.com","timestamp":1662951602245672889,"times":[{"rtt":2345923525},{"rtt":58430671},{"rtt":69273470},{"rtt":42784559},{"rtt":64318641}],"threshold":400000000,"healthy":true},{"title":"parkermoo.re","endpoint":"https://parkermoo.re","timestamp":1662951602246609744,"times":[{"rtt":2339567733},{"rtt":243317685},{"rtt":226849358},{"rtt":226824033},{"rtt":226948060}],"threshold":400000000,"healthy":true},{"title":"gossip.parkermoo.re","endpoint":"https://gossip.parkermoo.re","timestamp":1662951602245627338,"times":[{"rtt":2431750510},{"rtt":233702247},{"rtt":227901415},{"rtt":221134391},{"rtt":223482096}],"threshold":400000000,"healthy":true},{"title":"irc.parkermoo.re","endpoint":"https://irc.parkermoo.re","timestamp":1662951602245808429,"times":[{"rtt":2383940384},{"rtt":231435005},{"rtt":229219864},{"rtt":226731006},{"rtt":226911809}],"threshold":400000000,"healthy":true},{"title":"ping.parkermoo.re","endpoint":"https://ping.parkermoo.re/_health","timestamp":1662951602245864218,"times":[{"rtt":2376329983},{"rtt":218769248},{"rtt":237761321},{"rtt":225709388},{"rtt":225339581}],"threshold":400000000,"healthy":true},{"title":"stuff.parkermoore.de","endpoint":"https://stuff.parkermoore.de","timestamp":1662951604829423411,"times":[{"rtt":148052739},{"rtt":38142899},{"rtt":35072905},{"rtt":52366697},{"rtt":47912341}],"threshold":400000000,"healthy":true},{"title":"stash.byparker.com","endpoint":"https://stash.byparker.com","timestamp":1662951605151698368,"times":[{"rtt":167996066},{"rtt":52532513},{"rtt":71385196},{"rtt":40871624},{"rtt":60460495}],"threshold":400000000,"healthy":true},{"title":"keltermoore.com","endpoint":"https://www.keltermoore.com","timestamp":1662951605521688901,"times":[{"rtt":179989900},{"rtt":91388088},{"rtt":54766754},{"rtt":57732933},{"rtt":38724323}],"threshold":400000000,"healthy":true},{"title":"plex server","endpoint":"http://127.0.0.1:32400","timestamp":1662951605530627602,"times":[{"rtt":2427232}],"threshold":10000000,"healthy":true},{"title":"plants","endpoint":"https://plants.keltermoore.com/ping","timestamp":1662951605533230087,"times":[{"rtt":284537841},{"rtt":234396434},{"rtt":238387533},{"rtt":238861379},{"rtt":240002449}],"threshold":400000000,"healthy":true},{"title":"parker.codes","endpoint":"https://parker.codes/","timestamp":1662951605544738936,"times":[{"rtt":244930915}],"threshold":400000000,"healthy":true}]