[{"title":"byparker.com","endpoint":"https://byparker.com","timestamp":1675985401565002064,"times":[{"rtt":204287163},{"rtt":67350756},{"rtt":71682441},{"rtt":73242371},{"rtt":57984249}],"threshold":400000000,"healthy":true},{"title":"parkermoo.re","endpoint":"https://parkermoo.re","timestamp":1675985401565457810,"times":[{"rtt":94902691},{"rtt":50769335},{"rtt":53307709},{"rtt":42503475},{"rtt":45626773}],"threshold":400000000,"healthy":true},{"title":"gossip.parkermoo.re","endpoint":"https://gossip.parkermoo.re","timestamp":1675985401564806935,"times":[{"rtt":99410391},{"rtt":57037144},{"rtt":60150729},{"rtt":45850965},{"rtt":47861654}],"threshold":400000000,"healthy":true},{"title":"irc.parkermoo.re","endpoint":"https://irc.parkermoo.re","timestamp":1675985401565284907,"times":[{"rtt":98029265},{"rtt":47779139},{"rtt":53464112},{"rtt":53741143},{"rtt":52075823}],"threshold":400000000,"healthy":true},{"title":"ping.parkermoo.re","endpoint":"https://ping.parkermoo.re/_health","timestamp":1675985401564889149,"times":[{"rtt":99663647},{"rtt":48806884},{"rtt":54971979},{"rtt":50393778},{"rtt":57730420}],"threshold":400000000,"healthy":true},{"title":"stuff.parkermoore.de","endpoint":"https://stuff.parkermoore.de","timestamp":1675985401853446222,"times":[{"rtt":136599050},{"rtt":51594538},{"rtt":233673358},{"rtt":43765486},{"rtt":55250422}],"threshold":400000000,"healthy":true},{"title":"stash.byparker.com","endpoint":"https://stash.byparker.com","timestamp":1675985401871044026,"times":[{"rtt":155799935},{"rtt":47093014},{"rtt":52555220},{"rtt":55456675},{"rtt":45525320}],"threshold":400000000,"healthy":true},{"title":"keltermoore.com","endpoint":"https://www.keltermoore.com","timestamp":1675985401876247102,"times":[{"rtt":148613671},{"rtt":64561665},{"rtt":40745590},{"rtt":69015714},{"rtt":64379699}],"threshold":400000000,"healthy":true},{"title":"plex server","endpoint":"http://127.0.0.1:32400","timestamp":1675985401877132569,"times":[{"rtt":1442678}],"threshold":10000000,"healthy":true},{"title":"parker.codes","endpoint":"https://parker.codes/","timestamp":1675985401878799952,"times":[{"rtt":49293756}],"threshold":400000000,"healthy":true}]