[{"title":"byparker.com","endpoint":"https://byparker.com","timestamp":1681639202179577096,"times":[{"rtt":173733426},{"rtt":34699792},{"rtt":82514745},{"rtt":38800711},{"rtt":44670678}],"threshold":400000000,"healthy":true},{"title":"parkermoo.re","endpoint":"https://parkermoo.re","timestamp":1681639202180330686,"times":[{"rtt":83922086},{"rtt":41415963},{"rtt":38852862},{"rtt":39525201},{"rtt":46643430}],"threshold":400000000,"healthy":true},{"title":"gossip.parkermoo.re","endpoint":"https://gossip.parkermoo.re","timestamp":1681639202179643472,"times":[{"rtt":84314956},{"rtt":36741195},{"rtt":38886838},{"rtt":41602080},{"rtt":39169568}],"threshold":400000000,"healthy":true},{"title":"irc.parkermoo.re","endpoint":"https://irc.parkermoo.re","timestamp":1681639202180621567,"times":[{"rtt":78245935},{"rtt":41035306},{"rtt":41002817},{"rtt":40537571},{"rtt":39225431}],"threshold":400000000,"healthy":true},{"title":"ping.parkermoo.re","endpoint":"https://ping.parkermoo.re/_health","timestamp":1681639202178844719,"times":[{"rtt":82941891},{"rtt":49588138},{"rtt":44347872},{"rtt":33362153},{"rtt":44777330}],"threshold":400000000,"healthy":true},{"title":"stuff.parkermoore.de","endpoint":"https://stuff.parkermoore.de","timestamp":1681639202421498757,"times":[{"rtt":125901273},{"rtt":52400645},{"rtt":47878517},{"rtt":36197634},{"rtt":44870869}],"threshold":400000000,"healthy":true},{"title":"stash.byparker.com","endpoint":"https://stash.byparker.com","timestamp":1681639202422379912,"times":[{"rtt":135234259},{"rtt":52284330},{"rtt":37672501},{"rtt":31918024},{"rtt":73009068}],"threshold":400000000,"healthy":true},{"title":"keltermoore.com","endpoint":"https://www.keltermoore.com","timestamp":1681639202431458868,"times":[{"rtt":141302268},{"rtt":49600014},{"rtt":44291758},{"rtt":35199977},{"rtt":42861629}],"threshold":400000000,"healthy":true},{"title":"plex server","endpoint":"http://127.0.0.1:32400","timestamp":1681639202434671107,"times":[{"rtt":1797686}],"threshold":10000000,"healthy":true},{"title":"parker.codes","endpoint":"https://parker.codes/","timestamp":1681639202436680859,"times":[{"rtt":38370328}],"threshold":400000000,"healthy":true}]