[{"title":"byparker.com","endpoint":"https://byparker.com","timestamp":1690966802238231182,"times":[{"rtt":216247356},{"rtt":64261077},{"rtt":46990750},{"rtt":54959694},{"rtt":58736906}],"threshold":400000000,"healthy":true},{"title":"parkermoo.re","endpoint":"https://parkermoo.re","timestamp":1690966802238746817,"times":[{"rtt":389889585},{"rtt":74548692},{"rtt":98217483},{"rtt":89021814},{"rtt":55462467}],"threshold":400000000,"healthy":true},{"title":"gossip.parkermoo.re","endpoint":"https://gossip.parkermoo.re","timestamp":1690966802239183113,"times":[{"rtt":245167513},{"rtt":72936173},{"rtt":106090037},{"rtt":80776978},{"rtt":74786484}],"threshold":400000000,"healthy":true},{"title":"irc.parkermoo.re","endpoint":"https://irc.parkermoo.re","timestamp":1690966802239539632,"times":[{"rtt":293821420},{"rtt":87192028},{"rtt":82344334},{"rtt":61576574},{"rtt":91871008}],"threshold":400000000,"healthy":true},{"title":"ping.parkermoo.re","endpoint":"https://ping.parkermoo.re/_health","timestamp":1690966802237145785,"times":[{"rtt":282432083},{"rtt":101580836},{"rtt":81653020},{"rtt":102275975},{"rtt":87349482}],"threshold":400000000,"healthy":true},{"title":"stuff.parkermoore.de","endpoint":"https://stuff.parkermoore.de","timestamp":1690966802679978675,"times":[{"rtt":315867041},{"rtt":61679477},{"rtt":45536908},{"rtt":46758858},{"rtt":50316665}],"threshold":400000000,"healthy":true},{"title":"stash.byparker.com","endpoint":"https://stash.byparker.com","timestamp":1690966802819639998,"times":[{"rtt":138005729},{"rtt":43740311},{"rtt":57464368},{"rtt":58710468},{"rtt":47464034}],"threshold":400000000,"healthy":true},{"title":"keltermoore.com","endpoint":"https://www.keltermoore.com","timestamp":1690966802857183112,"times":[{"rtt":140803683},{"rtt":43852838},{"rtt":47039651},{"rtt":48697471},{"rtt":47369770}],"threshold":400000000,"healthy":true},{"title":"plex server","endpoint":"http://100.101.155.75:32400","timestamp":1690966802893663618,"times":[{"rtt":9201244}],"threshold":30000000,"healthy":true},{"title":"parker.codes","endpoint":"https://parker.codes/","timestamp":1690966802902972951,"times":[{"rtt":64073761}],"threshold":400000000,"healthy":true}]