[{"title":"byparker.com","endpoint":"https://byparker.com","timestamp":1697133602008059625,"times":[{"rtt":189711403},{"rtt":89342624},{"rtt":77319488},{"rtt":90219267},{"rtt":99952322}],"threshold":400000000,"healthy":true},{"title":"parkermoo.re","endpoint":"https://parkermoo.re","timestamp":1697133602006917515,"times":[{"rtt":131779848},{"rtt":197406593},{"rtt":112133461},{"rtt":225056576},{"rtt":154500522}],"threshold":400000000,"healthy":true},{"title":"gossip.parkermoo.re","endpoint":"https://gossip.parkermoo.re","timestamp":1697133602008574760,"times":[{"rtt":151365435},{"rtt":147350168},{"rtt":123875555},{"rtt":241477612},{"rtt":200852073}],"threshold":400000000,"healthy":true},{"title":"irc.parkermoo.re","endpoint":"https://irc.parkermoo.re","timestamp":1697133602008580060,"times":[{"rtt":151203869},{"rtt":130527874},{"rtt":109421720},{"rtt":97595824},{"rtt":291425334}],"threshold":400000000,"healthy":true},{"title":"ping.parkermoo.re","endpoint":"https://ping.parkermoo.re/_health","timestamp":1697133602006768699,"times":[{"rtt":201875393},{"rtt":171529670},{"rtt":118425585},{"rtt":181900549},{"rtt":204399105}],"threshold":400000000,"healthy":true},{"title":"stuff.parkermoore.de","endpoint":"https://stuff.parkermoore.de","timestamp":1697133602555682973,"times":[{"rtt":198537465},{"rtt":90825228},{"rtt":53343952},{"rtt":55199051},{"rtt":73319196}],"threshold":400000000,"healthy":true},{"title":"stash.byparker.com","endpoint":"https://stash.byparker.com","timestamp":1697133602789959318,"times":[{"rtt":241963884},{"rtt":75729243},{"rtt":86421317},{"rtt":106516750},{"rtt":113329785}],"threshold":400000000,"healthy":true},{"title":"keltermoore.com","endpoint":"https://www.keltermoore.com","timestamp":1697133602828819659,"times":[{"rtt":151713392},{"rtt":62729412},{"rtt":111352121},{"rtt":78366082},{"rtt":119187063}],"threshold":400000000,"healthy":true},{"title":"plex server","endpoint":"http://100.101.155.75:32400","timestamp":1697133602875440841,"times":[{"rtt":94353835}],"threshold":30000000,"degraded":true,"notice":"median round trip time exceeded threshold (30ms)"},{"title":"parker.codes","endpoint":"https://parker.codes/","timestamp":1697133602885697131,"times":[{"rtt":96909486}],"threshold":400000000,"healthy":true},{"title":"local dns","endpoint":"10.0.1.53:53","timestamp":1697133602970091833,"times":[{"rtt":10962504}],"threshold":30000000000,"healthy":true},{"title":"remote dns","endpoint":"100.100.217.128:53","timestamp":1697133602981080124,"times":[{"rtt":42986798}],"threshold":30000000000,"healthy":true}]