[{"title":"byparker.com","endpoint":"https://byparker.com","timestamp":1714698002171366620,"times":[{"rtt":270094356},{"rtt":37779605},{"rtt":49666109},{"rtt":72715317},{"rtt":49499606}],"threshold":400000000,"healthy":true},{"title":"parkermoo.re","endpoint":"https://parkermoo.re","timestamp":1714698002171111052,"times":[{"rtt":411022917},{"rtt":96802883},{"rtt":136316297},{"rtt":169934995},{"rtt":162857235}],"threshold":400000000,"healthy":true},{"title":"gossip.parkermoo.re","endpoint":"https://gossip.parkermoo.re","timestamp":1714698002171322644,"times":[{"rtt":190966514,"error":"Get \"https://gossip.parkermoo.re\": tls: failed to verify certificate: x509: certificate is valid for archive.bx.parkermakes.tools, not gossip.parkermoo.re"},{"rtt":72525851,"error":"Get \"https://gossip.parkermoo.re\": tls: failed to verify certificate: x509: certificate is valid for archive.bx.parkermakes.tools, not gossip.parkermoo.re"},{"rtt":47409153,"error":"Get \"https://gossip.parkermoo.re\": tls: failed to verify certificate: x509: certificate is valid for archive.bx.parkermakes.tools, not gossip.parkermoo.re"},{"rtt":56106909,"error":"Get \"https://gossip.parkermoo.re\": tls: failed to verify certificate: x509: certificate is valid for archive.bx.parkermakes.tools, not gossip.parkermoo.re"},{"rtt":112476723,"error":"Get \"https://gossip.parkermoo.re\": tls: failed to verify certificate: x509: certificate is valid for archive.bx.parkermakes.tools, not gossip.parkermoo.re"}],"threshold":400000000,"down":true},{"title":"irc.parkermoo.re","endpoint":"https://irc.parkermoo.re","timestamp":1714698002173990183,"times":[{"rtt":145260131,"error":"Get \"https://irc.parkermoo.re\": tls: failed to verify certificate: x509: certificate is valid for archive.bx.parkermakes.tools, not irc.parkermoo.re"},{"rtt":52304486,"error":"Get \"https://irc.parkermoo.re\": tls: failed to verify certificate: x509: certificate is valid for archive.bx.parkermakes.tools, not irc.parkermoo.re"},{"rtt":67586394,"error":"Get \"https://irc.parkermoo.re\": tls: failed to verify certificate: x509: certificate is valid for archive.bx.parkermakes.tools, not irc.parkermoo.re"},{"rtt":69563982,"error":"Get \"https://irc.parkermoo.re\": tls: failed to verify certificate: x509: certificate is valid for archive.bx.parkermakes.tools, not irc.parkermoo.re"},{"rtt":106095651,"error":"Get \"https://irc.parkermoo.re\": tls: failed to verify certificate: x509: certificate is valid for archive.bx.parkermakes.tools, not irc.parkermoo.re"}],"threshold":400000000,"down":true},{"title":"ping.parkermoo.re","endpoint":"https://ping.parkermoo.re/_health","timestamp":1714698002171449659,"times":[{"rtt":154527235,"error":"Get \"https://ping.parkermoo.re/_health\": tls: failed to verify certificate: x509: certificate is valid for archive.bx.parkermakes.tools, not ping.parkermoo.re"},{"rtt":74984449,"error":"Get \"https://ping.parkermoo.re/_health\": tls: failed to verify certificate: x509: certificate is valid for archive.bx.parkermakes.tools, not ping.parkermoo.re"},{"rtt":70757342,"error":"Get \"https://ping.parkermoo.re/_health\": tls: failed to verify certificate: x509: certificate is valid for archive.bx.parkermakes.tools, not ping.parkermoo.re"},{"rtt":106479770,"error":"Get \"https://ping.parkermoo.re/_health\": tls: failed to verify certificate: x509: certificate is valid for archive.bx.parkermakes.tools, not ping.parkermoo.re"},{"rtt":74253172,"error":"Get \"https://ping.parkermoo.re/_health\": tls: failed to verify certificate: x509: certificate is valid for archive.bx.parkermakes.tools, not ping.parkermoo.re"}],"threshold":400000000,"down":true},{"title":"stuff.parkermoore.de","endpoint":"https://stuff.parkermoore.de","timestamp":1714698002614945853,"times":[{"rtt":152818490},{"rtt":55210554},{"rtt":69900200},{"rtt":61668841},{"rtt":51719637}],"threshold":400000000,"healthy":true},{"title":"stash.byparker.com","endpoint":"https://stash.byparker.com","timestamp":1714698002651153590,"times":[{"rtt":134747954},{"rtt":75982618},{"rtt":100230986},{"rtt":64503684},{"rtt":79420047}],"threshold":400000000,"healthy":true},{"title":"keltermoore.com","endpoint":"https://www.keltermoore.com","timestamp":1714698002651905830,"times":[{"rtt":133638632},{"rtt":70764567},{"rtt":83105106},{"rtt":65232485},{"rtt":83036942}],"threshold":400000000,"healthy":true},{"title":"plex server","endpoint":"http://100.95.38.4:32400","timestamp":1714698002652615281,"times":[{"rtt":13509336,"error":"Get \"http://100.95.38.4:32400\": EOF"}],"threshold":30000000,"down":true},{"title":"parker.codes","endpoint":"https://parker.codes/","timestamp":1714698002666173306,"times":[{"rtt":119650575}],"threshold":400000000,"healthy":true},{"title":"local dns","endpoint":"10.0.1.53:53","timestamp":1714698002786112411,"times":[{"rtt":11258542}],"threshold":30000000000,"healthy":true},{"title":"remote dns","endpoint":"100.100.217.128:53","timestamp":1714698002797435304,"times":[{"rtt":38146925}],"threshold":30000000000,"healthy":true}]