[{"title":"byparker.com","endpoint":"https://byparker.com","timestamp":1719451802255008594,"times":[{"rtt":182424374},{"rtt":41537578},{"rtt":52551598},{"rtt":34491931},{"rtt":42700307}],"threshold":400000000,"healthy":true},{"title":"parkermoo.re","endpoint":"https://parkermoo.re","timestamp":1719451802254730025,"times":[{"rtt":157475588},{"rtt":84270949},{"rtt":96804243},{"rtt":117991423},{"rtt":68075577}],"threshold":400000000,"healthy":true},{"title":"gossip.parkermoo.re","endpoint":"https://gossip.parkermoo.re","timestamp":1719451802257039581,"times":[{"rtt":160913360},{"rtt":111782459},{"rtt":105674297},{"rtt":149644847},{"rtt":107344813}],"threshold":400000000,"healthy":true},{"title":"irc.parkermoo.re","endpoint":"https://irc.parkermoo.re","timestamp":1719451802257034394,"times":[{"rtt":165017923},{"rtt":135940162},{"rtt":77483757},{"rtt":76196451},{"rtt":93297307}],"threshold":400000000,"healthy":true},{"title":"ping.parkermoo.re","endpoint":"https://ping.parkermoo.re/_health","timestamp":1719451802254742100,"times":[{"rtt":163476711},{"rtt":139809544},{"rtt":115800382},{"rtt":109067942},{"rtt":116126402}],"threshold":400000000,"healthy":true},{"title":"stuff.parkermoore.de","endpoint":"https://stuff.parkermoore.de","timestamp":1719451802609632929,"times":[{"rtt":161889734},{"rtt":54108373},{"rtt":44130829},{"rtt":82080658},{"rtt":43028165}],"threshold":400000000,"healthy":true},{"title":"stash.byparker.com","endpoint":"https://stash.byparker.com","timestamp":1719451802780672538,"times":[{"rtt":142749367},{"rtt":39422802},{"rtt":41518053},{"rtt":44964124},{"rtt":39156945}],"threshold":400000000,"healthy":true},{"title":"keltermoore.com","endpoint":"https://www.keltermoore.com","timestamp":1719451802805898780,"times":[{"rtt":133198270},{"rtt":38920889},{"rtt":44919398},{"rtt":46291195},{"rtt":42604404}],"threshold":400000000,"healthy":true},{"title":"plex server","endpoint":"http://100.95.38.4:32400/identity","timestamp":1719451802894013160,"times":[{"rtt":28143175}],"threshold":30000000,"healthy":true},{"title":"parker.codes","endpoint":"https://parker.codes/","timestamp":1719451802900185711,"times":[{"rtt":141278355}],"threshold":400000000,"healthy":true},{"title":"local dns","endpoint":"10.0.1.53:53","timestamp":1719451802922393416,"times":[{"rtt":12166073}],"threshold":30000000000,"healthy":true},{"title":"remote dns","endpoint":"100.100.217.128:53","timestamp":1719451802934602202,"times":[{"rtt":61150733}],"threshold":30000000000,"healthy":true}]