[{"title":"byparker.com","endpoint":"https://byparker.com","timestamp":1722988801533802623,"times":[{"rtt":318601191},{"rtt":39852565},{"rtt":45672657},{"rtt":39482708},{"rtt":43600079}],"threshold":400000000,"healthy":true},{"title":"parkermoo.re","endpoint":"https://parkermoo.re","timestamp":1722988801533854662,"times":[{"rtt":377408438},{"rtt":303489362},{"rtt":644375638},{"rtt":746306064},{"rtt":543777261}],"threshold":400000000,"degraded":true,"notice":"median round trip time exceeded threshold (400ms)"},{"title":"gossip.parkermoo.re","endpoint":"https://gossip.parkermoo.re","timestamp":1722988801534748730,"times":[{"rtt":485938512},{"rtt":325277800},{"rtt":769364580},{"rtt":664017632},{"rtt":596617848}],"threshold":400000000,"degraded":true,"notice":"median round trip time exceeded threshold (400ms)"},{"title":"irc.parkermoo.re","endpoint":"https://irc.parkermoo.re","timestamp":1722988801541683582,"times":[{"rtt":529299747},{"rtt":656217702},{"rtt":559921699},{"rtt":746078096},{"rtt":478690174}],"threshold":400000000,"degraded":true,"notice":"median round trip time exceeded threshold (400ms)"},{"title":"ping.parkermoo.re","endpoint":"https://ping.parkermoo.re/_health","timestamp":1722988801536770733,"times":[{"rtt":673013079},{"rtt":908561633},{"rtt":778467750},{"rtt":596697799},{"rtt":130465526}],"threshold":400000000,"degraded":true,"notice":"median round trip time exceeded threshold (400ms)"},{"title":"stuff.parkermoore.de","endpoint":"https://stuff.parkermoore.de","timestamp":1722988802021600660,"times":[{"rtt":366226799},{"rtt":33831094},{"rtt":58284548},{"rtt":45824023},{"rtt":53469952}],"threshold":400000000,"healthy":true},{"title":"stash.byparker.com","endpoint":"https://stash.byparker.com","timestamp":1722988802580477702,"times":[{"rtt":172980221},{"rtt":54693839},{"rtt":75806814},{"rtt":56376323},{"rtt":40709932}],"threshold":400000000,"healthy":true},{"title":"keltermoore.com","endpoint":"https://www.keltermoore.com","timestamp":1722988802982935231,"times":[{"rtt":448892850},{"rtt":53142970},{"rtt":55239250},{"rtt":65211100},{"rtt":62821027}],"threshold":400000000,"healthy":true},{"title":"plex server","endpoint":"http://100.95.38.4:32400/identity","timestamp":1722988803669539318,"times":[{"rtt":7566290}],"threshold":30000000,"healthy":true},{"title":"parker.codes","endpoint":"https://parker.codes/","timestamp":1722988803677399014,"times":[{"rtt":812920716}],"threshold":400000000,"degraded":true,"notice":"median round trip time exceeded threshold (400ms)"},{"title":"local dns","endpoint":"10.0.1.53:53","timestamp":1722988804150728619,"times":[{"rtt":24562281}],"threshold":30000000000,"healthy":true},{"title":"remote dns","endpoint":"100.100.217.128:53","timestamp":1722988804175441466,"times":[{"rtt":73708972}],"threshold":30000000000,"healthy":true}]